rvmath/__init__.py
rvmath/base.py
rvmath/testsuite/__init__.py
rvmath/testsuite/test_construction.py
rvmath/testsuite/test_rvs.py
rvmath/testsuite/test_str_repr.py
rvmath/testsuite/test_to_distro.py
rvmath-0.1.dist-info/AUTHORS
rvmath-0.1.dist-info/LICENSE
rvmath-0.1.dist-info/METADATA
rvmath-0.1.dist-info/WHEEL
rvmath-0.1.dist-info/top_level.txt
rvmath-0.1.dist-info/zip-safe
rvmath-0.1.dist-info/RECORD
